pysmartweatherudp/__init__.py
pysmartweatherudp/constants.py
pysmartweatherudp/receiver.py
pysmartweatherudp/utils.py
pysmartweatherudp-0.1.6.dist-info/LICENSE
pysmartweatherudp-0.1.6.dist-info/METADATA
pysmartweatherudp-0.1.6.dist-info/WHEEL
pysmartweatherudp-0.1.6.dist-info/top_level.txt
pysmartweatherudp-0.1.6.dist-info/RECORD
