Metadata-Version: 2.1
Name: pysmartweatherudp
Version: 0.1.6
Summary: Receive data from Smart Weather via UDP
Home-page: https://github.com/briis/pysmartweatherudp
Author: Bjarne Riis
Author-email: bjarne@briis.com
License: MIT
Keywords: smartweather weatherflow home-assistant
Platform: UNKNOWN
Classifier: Development Status :: 4 - Beta
Classifier: Intended Audience :: Developers
Classifier: Topic :: Software Development :: Build Tools
Classifier: License :: OSI Approved :: MIT License
Classifier: Programming Language :: Python :: 2
Classifier: Programming Language :: Python :: 2.6
Classifier: Programming Language :: Python :: 2.7
Classifier: Programming Language :: Python :: 3
Classifier: Programming Language :: Python :: 3.3
Classifier: Programming Language :: Python :: 3.4
Classifier: Programming Language :: Python :: 3.5
Provides-Extra: dev
Requires-Dist: check-manifest ; extra == 'dev'
Provides-Extra: test
Requires-Dist: coverage ; extra == 'test'
